LICENSE
README.md
afkode/__init__.py
afkode/action.py
afkode/api.py
afkode/commands/0_template.py
afkode/commands/__init__.py
afkode/commands/keyword_search.py
afkode/commands/list_actions.py
afkode/commands/send_latest_agent_response_to_notes.py
afkode/commands/send_latest_transcription_to_chat.py
afkode/commands/send_latest_transcription_to_notes.py
afkode/commands/suggest_program_actions.py
afkode/commands/suggest_program_functionality.py
afkode/commands/suggest_program_improvements.py
afkode/commands/suggest_program_tests.py
afkode/commands/summarize_filename.py
afkode/commands/summarize_today.py
afkode/config.json
afkode/globals.py
afkode/ios/__init__.py
afkode/ios/listen.py
afkode/ios/speech.py
afkode/macos/__init__.py
afkode/macos/blip.wav
afkode/macos/listen.py
afkode/macos/speech.py
afkode/meta.py
afkode/prompts/debug/nox_tests.txt
afkode/prompts/debug/program_actions.txt
afkode/prompts/debug/program_functionality.txt
afkode/prompts/debug/program_improvements.txt
afkode/prompts/debug/program_tests.txt
afkode/prompts/debug/whisper_hallucinations.txt
afkode/prompts/programflow/choose_command.txt
afkode/prompts/programflow/harmonize_transcripts.txt
afkode/prompts/programflow/proposed_filename.txt
afkode/prompts/programflow/user_input_assist.txt
afkode/run.py
afkode/set_env.py
afkode/utils.py
afkode/voice_interface.py
afkode-0.4.4.dist-info/entry_points.txt
afkode-0.4.4.dist-info/LICENSE
afkode-0.4.4.dist-info/WHEEL
afkode-0.4.4.dist-info/METADATA
afkode-0.4.4.dist-info/RECORD
