Metadata-Version: 2.1
Name: afkode
Version: 0.4.4
Summary: Personal voice command interface for iPhone on pythonista powered by Whisper and ChatGPT.
Home-page: https://www.ndjenkins.com/
License: MIT
Keywords: quick_start,python_packaging,whisper,chatgpt,openai
Author: Nick Jenkins
Requires-Python: >=3.8.1,<3.9
Classifier: Development Status :: 4 - Beta
Classifier: Intended Audience :: Developers
Classifier: Intended Audience :: Education
Classifier: License :: OSI Approved :: MIT License
Classifier: Programming Language :: Python :: 3
Classifier: Programming Language :: Python :: 3 :: Only
Classifier: Topic :: Documentation
Classifier: Topic :: Documentation :: Sphinx
Classifier: Topic :: Education :: Testing
Classifier: Topic :: Software Development :: Build Tools
Classifier: Topic :: Software Development :: Documentation
Classifier: Topic :: Software Development :: Libraries
Classifier: Topic :: Utilities
Provides-Extra: docs
Provides-Extra: lint
Provides-Extra: tests
Requires-Dist: PyAudio (>=0.2.13,<0.3.0)
Requires-Dist: PyYAML (>=6.0,<7.0)
Requires-Dist: black (>=23.3,<24.0); extra == "lint"
Requires-Dist: darglint (>=1.8,<2.0); extra == "lint"
Requires-Dist: flake8 (>=6.0,<7.0); extra == "lint"
Requires-Dist: flake8-annotations (>=3.0,<4.0); extra == "lint"
Requires-Dist: flake8-bandit (>=4.1,<5.0); extra == "lint"
Requires-Dist: flake8-bugbear (>=23.6,<24.0); extra == "lint"
Requires-Dist: flake8-builtins (>=2.1,<3.0); extra == "lint"
Requires-Dist: flake8-docstrings (>=1.7,<2.0); extra == "lint"
Requires-Dist: gTTS (>=2.3.2,<3.0.0)
Requires-Dist: google-auth (==2.22.0)
Requires-Dist: m2r2 (>=0.3,<0.4); extra == "docs"
Requires-Dist: mypy (>=0.910,<0.911); extra == "lint"
Requires-Dist: openai (>=0.27.5,<0.28.0)
Requires-Dist: pydub (>=0.25.1,<0.26.0)
Requires-Dist: pytest (>=6.2,<7.0); extra == "tests"
Requires-Dist: pytest-cases (>=3.6,<4.0); extra == "tests"
Requires-Dist: pytest-cov (>=3.0,<4.0); extra == "tests"
Requires-Dist: requests (>=2.23.0,<3.0.0)
Requires-Dist: requests_toolbelt (>=1.0.0,<2.0.0)
Requires-Dist: safety (>=2.3,<3.0); extra == "lint"
Requires-Dist: sphinx (>=6.2,<7.0); extra == "docs"
Requires-Dist: sphinx-autodoc-typehints (>=1.23,<2.0); extra == "docs"
Requires-Dist: sphinx_rtd_theme (>=1.2,<2.0); extra == "docs"
Requires-Dist: types-PyYAML (>=6.0,<7.0); extra == "lint"
Requires-Dist: types-requests (>=2.31.0,<3.0.0)
Requires-Dist: urllib3 (==1.26.16)
Requires-Dist: xdoctest (>=1.1,<2.0); extra == "lint"
Project-URL: Documentation, https://ndjenkins85.github.io/afkode/
Project-URL: Repository, https://github.com/ndjenkins85/afkode/
